MANIFEST.in
README.md
setup.cfg
setup.py
src/pytal/__init__.py
src/pytal/pytal.py
src/pytal.egg-info/PKG-INFO
src/pytal.egg-info/SOURCES.txt
src/pytal.egg-info/dependency_links.txt
src/pytal.egg-info/top_level.txt
src/pytal/monitor/build/asset-manifest.json
src/pytal/monitor/build/favicon.ico
src/pytal/monitor/build/index.html
src/pytal/monitor/build/logo192.png
src/pytal/monitor/build/logo512.png
src/pytal/monitor/build/manifest.json
src/pytal/monitor/build/precache-manifest.98b4ae3539e4c83c98d78bb25f6d455f.js
src/pytal/monitor/build/robots.txt
src/pytal/monitor/build/service-worker.js
src/pytal/monitor/build/static/css/main.5f361e03.chunk.css
src/pytal/monitor/build/static/css/main.5f361e03.chunk.css.map
src/pytal/monitor/build/static/js/2.a72618c2.chunk.js
src/pytal/monitor/build/static/js/2.a72618c2.chunk.js.LICENSE.txt
src/pytal/monitor/build/static/js/2.a72618c2.chunk.js.map
src/pytal/monitor/build/static/js/main.2e705693.chunk.js
src/pytal/monitor/build/static/js/main.2e705693.chunk.js.map
src/pytal/monitor/build/static/js/runtime-main.b772fc2b.js
src/pytal/monitor/build/static/js/runtime-main.b772fc2b.js.map