Metadata-Version: 1.0
Name: pytal
Version: 0.1.0
Summary: Python Trade Analisis UI Library for Backtest, Forex Trade and Stock Trade
Home-page: UNKNOWN
Author: Rui Hirano
Author-email: UNKNOWN
License: UNKNOWN
Platform: UNKNOWN
